hahahellooo_lotto/__init__.py
hahahellooo_lotto/draw.py
hahahellooo_lotto-0.2.0.dist-info/METADATA
hahahellooo_lotto-0.2.0.dist-info/WHEEL
hahahellooo_lotto-0.2.0.dist-info/top_level.txt
hahahellooo_lotto-0.2.0.dist-info/RECORD
