Metadata-Version: 2.1
Name: hahahellooo_lotto
Version: 0.2.0
Summary: Default template for PDM package
Author-email: hahahellooo <hahahello777@gmail.com>
License: MIT
Requires-Python: >=3.9
